setup.cfg
setup.py
fr2csv/__init__.py
fr2csv.egg-info/PKG-INFO
fr2csv.egg-info/SOURCES.txt
fr2csv.egg-info/dependency_links.txt
fr2csv.egg-info/entry_points.txt
fr2csv.egg-info/requires.txt
fr2csv.egg-info/top_level.txt