Metadata-Version: 1.1
Name: fr2csv
Version: 1.0.1
Summary: Reads French localized AND normal CSVs, ouputs normal CSVs
Home-page: https://github.com/ewjoachim/fr2csv
Author: Joachim Jablon
Author-email: ewjoachim@gmail.com
License: UNKNOWN
Platform: UNKNOWN
Classifier: License :: OSI Approved :: MIT License
Classifier: Programming Language :: Python :: 2.7
